{
  "identifier": "com.vault.app",
  "productName": "Vault",
  "version": "0.1.0",
  "build": {
    "beforeDevCommand": "npm run dev",
    "beforeBuildCommand": "npm run build",
    "frontendDist": "../dist",
    "devUrl": "http://localhost:5173"
  },
  "bundle": {
    "active": true,
    "targets": "all",
    "icon": [
      "icons/icon.png"
    ],
    "resources": [],
    "externalBin": [
      "../mcp-servers/filesystem-server-rust/target/release/mcp-filesystem-server",
      "../mcp-servers/search-server-rust/target/release/mcp-search-server",
      "../mcp-servers/git-server-rust/target/release/mcp-git-server"
    ]
  },
  "app": {
    "macOSPrivateApi": true,
    "security": {
      "csp": null,
      "capabilities": ["main"]
    },
    "windows": [
      {
        "title": "",
        "width": 1200,
        "height": 800,
        "minWidth": 800,
        "minHeight": 600,
        "label": "main",
        "transparent": true
      }
    ]
  },
  "plugins": {
    "fs": {
      "requireLiteralLeadingDot": false
    },
    "shell": {
      "open": true
    }
  }
}